pyfirmwareman/__init__.py
pyfirmwareman/capifwb.so
pyfirmwareman/helper_configini.py
pyfirmwareman/main.py
pyfirmwareman/makebin_bootloaderkeys.py
pyfirmwareman/makebin_hex.py
pyfirmwareman/makebin_upgrade.py
pyfirmwareman/makexml_hex.py
pyfirmwareman/pyfirmwaremandef.py
pyfirmwareman/shared.py
pyfirmwareman-1.0.2.dist-info/LICENSE.txt
pyfirmwareman-1.0.2.dist-info/METADATA
pyfirmwareman-1.0.2.dist-info/WHEEL
pyfirmwareman-1.0.2.dist-info/entry_points.txt
pyfirmwareman-1.0.2.dist-info/top_level.txt
pyfirmwareman-1.0.2.dist-info/RECORD
